lbTool/Command.py
lbTool/Common.py
lbTool/CompressUtil.py
lbTool/Config.py
lbTool/ConfigManager.py
lbTool/Db.py
lbTool/DmDb.py
lbTool/EnCipher.py
lbTool/FileUtil.py
lbTool/Logging.py
lbTool/__init__.py
lbTool/config/config.yml
lbTool/config/log.yml
lbTool/hooks/__init__.py
lbTool/hooks/hook-dmPython.py
lbtool-1.6.0.dist-info/METADATA
lbtool-1.6.0.dist-info/WHEEL
lbtool-1.6.0.dist-info/top_level.txt
lbtool-1.6.0.dist-info/RECORD
