Metadata-Version: 2.4
Name: lbTool
Version: 1.6.0
Summary: Multifunctional Toolset
Author: lb
Author-email: lcoolb@163.com
Requires-Python: >=3.6, <3.11
Requires-Dist: requests
Requires-Dist: gmSsl==3.2.2
Requires-Dist: pycryptodome==3.18.0
Requires-Dist: pypdf2==3.0.1
Requires-Dist: pony==0.7.17
Requires-Dist: cx-Oracle==8.3.0
Requires-Dist: pymysql>=1.1.0
Requires-Dist: dmPython>=2.5.5
Requires-Dist: comtypes==1.2.0
Requires-Dist: pyyaml==6.0.1
Dynamic: author
Dynamic: author-email
Dynamic: description
Dynamic: description-content-type
Dynamic: requires-dist
Dynamic: requires-python
Dynamic: summary
